osos/__init__.py
osos/cli.py
osos/osos.py
osos/version.py
osos/api_conda/__init__.py
osos/api_conda/api_conda.py
osos/api_github/__init__.py
osos/api_github/api_github.py
osos/api_pypi/__init__.py
osos/api_pypi/api_pypi.py
osos/utilities/__init__.py
osos/utilities/plotting.py
NREL_osos-0.0.3.dist-info/LICENSE
NREL_osos-0.0.3.dist-info/METADATA
NREL_osos-0.0.3.dist-info/WHEEL
NREL_osos-0.0.3.dist-info/entry_points.txt
NREL_osos-0.0.3.dist-info/top_level.txt
NREL_osos-0.0.3.dist-info/RECORD
