Metadata-Version: 2.1
Name: NREL-osos
Version: 0.0.3
Summary: Open Source Ops and Statistics
Home-page: https://nrel.github.io/osos/
Author: Grant Buster
Author-email: grant.buster@nrel.gov
License: BSD 3-Clause
Keywords: osos
Platform: UNKNOWN
Classifier: Development Status :: 4 - Beta
Classifier: Intended Audience :: Science/Research
Classifier: License :: OSI Approved :: BSD License
Classifier: Natural Language :: English
Classifier: Programming Language :: Python :: 3.7
Classifier: Programming Language :: Python :: 3.8
Classifier: Programming Language :: Python :: 3.9
Requires-Python: >=3.7
Requires-Dist: click
Requires-Dist: nrel-rex
Requires-Dist: numpy
Requires-Dist: pandas
Requires-Dist: pypistats
Requires-Dist: requests
Requires-Dist: seaborn
Provides-Extra: dev
Requires-Dist: pytest (>=5.2) ; extra == 'dev'
Requires-Dist: flake8 ; extra == 'dev'
Requires-Dist: pre-commit ; extra == 'dev'
Requires-Dist: pylint ; extra == 'dev'
Provides-Extra: test
Requires-Dist: pytest (>=5.2) ; extra == 'test'
